genpypress/__init__.py
genpypress/app/app_cc/__init__.py
genpypress/app/app_deploy/app_deploy.py
genpypress/app/app_join/__init__.py
genpypress/app/app_logparser/__init__.py
genpypress/app/app_logparser/model.py
genpypress/app/app_logparser/parser.py
genpypress/app/app_patch_to_validtime/__init__.py
genpypress/app/app_rewrite/__init__.py
genpypress/app/app_rewrite/exceptions.py
genpypress/app/app_to_async/__init__.py
genpypress/app/app_transfer/transfer.py
genpypress/mapping/__init__.py
genpypress/ph.py
genpypress/table/__init__.py
genpypress/table/_bin/table2json.exe
genpypress/tera/__init__.py
genpypress/tera/ddl.py
genpypress/tera/session.py
genpypress-0.1.49.dist-info/LICENSE
genpypress-0.1.49.dist-info/METADATA
genpypress-0.1.49.dist-info/WHEEL
genpypress-0.1.49.dist-info/entry_points.txt
genpypress-0.1.49.dist-info/RECORD
