Metadata-Version: 2.1
Name: genpypress
Version: 0.1.49
Summary: Set of tools and utilities connected with press code generator.
License: MIT
Author: Jan Herout
Author-email: jan.herout@gmail.com
Requires-Python: >=3.10,<4.0
Classifier: Development Status :: 1 - Planning
Classifier: Environment :: Console
Classifier: Intended Audience :: Developers
Classifier: License :: OSI Approved :: MIT License
Classifier: Operating System :: Microsoft :: Windows
Classifier: Programming Language :: Python :: 3
Classifier: Programming Language :: Python :: 3.10
Classifier: Programming Language :: Python :: 3.11
Classifier: Programming Language :: Python :: 3.12
Classifier: Topic :: Database
Requires-Dist: attrs (>=22.2.0,<23.0.0)
Requires-Dist: cattrs (>=22.2.0,<23.0.0)
Requires-Dist: loguru (>=0.7.2,<0.8.0)
Requires-Dist: rich (>=13.3.3,<14.0.0)
Requires-Dist: teradatasql (>=20.0.0.16,<21.0.0.0)
Requires-Dist: typer[rich] (>=0.12.5,<0.13.0)
